the1conf/__init__.py
the1conf/app_config.py
the1conf/app_config_meta.py
the1conf/attr_dict.py
the1conf/auto_prolog.py
the1conf/click_option.py
the1conf/config_var.py
the1conf/flags.py
the1conf/py.typed
the1conf/solver.py
the1conf/utils.py
the1conf/var_substitution.py
the1conf-1.2.3.dist-info/METADATA
the1conf-1.2.3.dist-info/WHEEL
the1conf-1.2.3.dist-info/licenses/LICENSE
the1conf-1.2.3.dist-info/RECORD
