Metadata-Version: 2.4
Name: the1conf
Version: 1.2.3
Summary: All in one configuration management tool for your python applications.
License-Expression: MIT
License-File: LICENSE
Keywords: configuration,settings,cli,click,pydantic
Author: Eric CHASTAN
Author-email: eric@chastan.consulting
Requires-Python: >=3.12,<3.13
Classifier: Development Status :: 5 - Production/Stable
Classifier: Intended Audience :: Developers
Classifier: Operating System :: OS Independent
Classifier: Programming Language :: Python :: 3
Classifier: Programming Language :: Python :: 3.12
Classifier: Topic :: Software Development :: Libraries
Requires-Dist: click (>=8.3.1)
Requires-Dist: jinja2 (>=3.1.6)
Requires-Dist: pydantic (>=2.12.5)
Requires-Dist: toml (>=0.10.2)
Project-URL: Issues, https://gitlab.com/eric-chastan/the1conf/-/issues
Project-URL: Repository, https://gitlab.com/eric-chastan/the1conf
